Workbook

Sheet Summary
A1: Vibe Coding 損益表摘要
A2: 基於 docs/investor/12m-funding-plan.csv 的 12 個月營運預估
A4: Annual revenue | B4: =SUM('Monthly P&L'!C10:N10) | D4: Model note | E4: Operating profit excludes cash injection; financing is shown separately.
A5: Gross profit | B5: =SUM('Monthly P&L'!C17:N17)
A6: EBITDA | B6: =SUM('Monthly P&L'!C26:N26) | D6: Total revenue | E6: =SUM('Monthly P&L'!C10:N10)
A7: EBITDA margin | B7: =IFERROR(B6/B4,0) | D7: Total COGS | E7: =SUM('Monthly P&L'!C16:N16)
A8: Closing cash (M12) | B8: ='Monthly P&L'!N31 | D8: Total opex | E8: =SUM('Monthly P&L'!C25:N25)
D9: Net profit / EBITDA | E9: =SUM('Monthly P&L'!C26:N26)
D12: Month | E12: Revenue | F12: Gross profit | G12: EBITDA
D13: ='Monthly P&L'!C4 | E13: ='Monthly P&L'!C10 | F13: ='Monthly P&L'!C17 | G13: ='Monthly P&L'!C26
D14: ='Monthly P&L'!D4 | E14: ='Monthly P&L'!D10 | F14: ='Monthly P&L'!D17 | G14: ='Monthly P&L'!D26
D15: ='Monthly P&L'!E4 | E15: ='Monthly P&L'!E10 | F15: ='Monthly P&L'!E17 | G15: ='Monthly P&L'!E26
D16: ='Monthly P&L'!F4 | E16: ='Monthly P&L'!F10 | F16: ='Monthly P&L'!F17 | G16: ='Monthly P&L'!F26
D17: ='Monthly P&L'!G4 | E17: ='Monthly P&L'!G10 | F17: ='Monthly P&L'!G17 | G17: ='Monthly P&L'!G26
D18: ='Monthly P&L'!H4 | E18: ='Monthly P&L'!H10 | F18: ='Monthly P&L'!H17 | G18: ='Monthly P&L'!H26
D19: ='Monthly P&L'!I4 | E19: ='Monthly P&L'!I10 | F19: ='Monthly P&L'!I17 | G19: ='Monthly P&L'!I26
D20: ='Monthly P&L'!J4 | E20: ='Monthly P&L'!J10 | F20: ='Monthly P&L'!J17 | G20: ='Monthly P&L'!J26
D21: ='Monthly P&L'!K4 | E21: ='Monthly P&L'!K10 | F21: ='Monthly P&L'!K17 | G21: ='Monthly P&L'!K26
D22: ='Monthly P&L'!L4 | E22: ='Monthly P&L'!L10 | F22: ='Monthly P&L'!L17 | G22: ='Monthly P&L'!L26
D23: ='Monthly P&L'!M4 | E23: ='Monthly P&L'!M10 | F23: ='Monthly P&L'!M17 | G23: ='Monthly P&L'!M26
D24: ='Monthly P&L'!N4 | E24: ='Monthly P&L'!N10 | F24: ='Monthly P&L'!N17 | G24: ='Monthly P&L'!N26

Sheet Assumptions
A1: 損益表模型假設
A3: 模型期間 | B3: 12 個月預估
A4: 幣別 | B4: TWD / NT$
A5: 資料來源 | B5: docs/investor/12m-funding-plan.csv
A6: 模型性質 | B6: Internal planning P&L (not historical actuals)
A7: 損益範圍 | B7: Revenue, COGS, gross profit, opex, EBITDA
A8: 現金項目 | B8: Cash injection / ending cash shown separately as memo
A11: 說明
A12: 這份損益表是依據 12m-funding-plan.csv 製作，將營收、成本、費用與 EBITDA 分開呈現；現金注資與期末現金僅作補充資訊。

Sheet Source Data
A1: Source note | B1: Based on internal operating plan
A2: Source file | B2: docs/investor/12m-funding-plan.csv
A4: month | B4: paid_learners | C4: course_revenue_twd | D4: hardware_revenue_twd | E4: monthly_revenue_twd | F4: course_cogs_twd | G4: hardware_cogs_twd | H4: logistics_cost_twd | I4: payment_fee_twd | J4: monthly_cogs_twd | K4: gross_profit_twd | L4: team_cost_twd | M4: infra_tools_twd | N4: marketing_twd | O4: other_opex_twd | P4: total_opex_twd | Q4: ebitda_twd | R4: cash_injection_twd | S4: ending_cash_twd | T4: source_file
A5: M1 | B5: 300 | C5: 300000 | D5: 60000 | E5: 360000 | F5: 54000 | G5: 37200 | H5: 3000 | I5: 11520 | J5: 105720 | K5: 254280 | L5: 420000 | M5: 50000 | N5: 120000 | O5: 45000 | P5: 635000 | Q5: -380720 | R5: 8000000 | S5: 7619280 | T5: docs/investor/12m-funding-plan.csv
A6: M2 | B6: 360 | C6: 360000 | D6: 72000 | E6: 432000 | F6: 64800 | G6: 44640 | H6: 3600 | I6: 13824 | J6: 126864 | K6: 305136 | L6: 420000 | M6: 50000 | N6: 130000 | O6: 45000 | P6: 645000 | Q6: -339864 | R6: 0 | S6: 7279416 | T6: docs/investor/12m-funding-plan.csv
A7: M3 | B7: 430 | C7: 430000 | D7: 86000 | E7: 516000 | F7: 77400 | G7: 53320 | H7: 4300 | I7: 16512 | J7: 151532 | K7: 364468 | L7: 450000 | M7: 50000 | N7: 140000 | O7: 45000 | P7: 685000 | Q7: -320532 | R7: 0 | S7: 6958884 | T7: docs/investor/12m-funding-plan.csv
A8: M4 | B8: 520 | C8: 520000 | D8: 104000 | E8: 624000 | F8: 93600 | G8: 64480 | H8: 5200 | I8: 19968 | J8: 183248 | K8: 440752 | L8: 450000 | M8: 55000 | N8: 150000 | O8: 50000 | P8: 705000 | Q8: -264248 | R8: 0 | S8: 6694636 | T8: docs/investor/12m-funding-plan.csv
A9: M5 | B9: 620 | C9: 620000 | D9: 124000 | E9: 744000 | F9: 111600 | G9: 76880 | H9: 6200 | I9: 23808 | J9: 218488 | K9: 525512 | L9: 480000 | M9: 55000 | N9: 160000 | O9: 50000 | P9: 745000 | Q9: -219488 | R9: 0 | S9: 6475148 | T9: docs/investor/12m-funding-plan.csv
A10: M6 | B10: 740 | C10: 740000 | D10: 148000 | E10: 888000 | F10: 133200 | G10: 91760 | H10: 7400 | I10: 28416 | J10: 260776 | K10: 627224 | L10: 480000 | M10: 60000 | N10: 170000 | O10: 50000 | P10: 760000 | Q10: -132776 | R10: 0 | S10: 6342372 | T10: docs/investor/12m-funding-plan.csv
A11: M7 | B11: 900 | C11: 900000 | D11: 180000 | E11: 1080000 | F11: 162000 | G11: 111600 | H11: 9000 | I11: 34560 | J11: 317160 | K11: 762840 | L11: 520000 | M11: 60000 | N11: 190000 | O11: 55000 | P11: 825000 | Q11: -62160 | R11: 0 | S11: 6280212 | T11: docs/investor/12m-funding-plan.csv
A12: M8 | B12: 1100 | C12: 1100000 | D12: 220000 | E12: 1320000 | F12: 198000 | G12: 136400 | H12: 11000 | I12: 42240 | J12: 387640 | K12: 932360 | L12: 520000 | M12: 65000 | N12: 210000 | O12: 55000 | P12: 850000 | Q12: 82360 | R12: 0 | S12: 6362572 | T12: docs/investor/12m-funding-plan.csv
A13: M9 | B13: 1350 | C13: 1350000 | D13: 270000 | E13: 1620000 | F13: 243000 | G13: 167400 | H13: 13500 | I13: 51840 | J13: 475740 | K13: 1144260 | L13: 560000 | M13: 65000 | N13: 230000 | O13: 60000 | P13: 915000 | Q13: 229260 | R13: 0 | S13: 6591832 | T13: docs/investor/12m-funding-plan.csv
A14: M10 | B14: 1650 | C14: 1650000 | D14: 330000 | E14: 1980000 | F14: 297000 | G14: 204600 | H14: 16500 | I14: 63360 | J14: 581460 | K14: 1398540 | L14: 560000 | M14: 70000 | N14: 250000 | O14: 60000 | P14: 940000 | Q14: 458540 | R14: 0 | S14: 7050372 | T14: docs/investor/12m-funding-plan.csv
A15: M11 | B15: 1950 | C15: 1950000 | D15: 390000 | E15: 2340000 | F15: 351000 | G15: 241800 | H15: 19500 | I15: 74880 | J15: 687180 | K15: 1652820 | L15: 600000 | M15: 70000 | N15: 270000 | O15: 65000 | P15: 1005000 | Q15: 647820 | R15: 0 | S15: 7698192 | T15: docs/investor/12m-funding-plan.csv
A16: M12 | B16: 2200 | C16: 2200000 | D16: 440000 | E16: 2640000 | F16: 396000 | G16: 272800 | H16: 22000 | I16: 84480 | J16: 775280 | K16: 1864720 | L16: 600000 | M16: 70000 | N16: 300000 | O16: 65000 | P16: 1035000 | Q16: 829720 | R16: 0 | S16: 8527912 | T16: docs/investor/12m-funding-plan.csv

Sheet Monthly P&L
A1: 12 個月損益表
A2: 來源：docs/investor/12m-funding-plan.csv
A4: 項目 | C4: M1 | D4: M2 | E4: M3 | F4: M4 | G4: M5 | H4: M6 | I4: M7 | J4: M8 | K4: M9 | L4: M10 | M4: M11 | N4: M12
A6: Revenue
A7: Paid learners | C7: ='Source Data'!$B$5 | D7: ='Source Data'!$B$6 | E7: ='Source Data'!$B$7 | F7: ='Source Data'!$B$8 | G7: ='Source Data'!$B$9 | H7: ='Source Data'!$B$10 | I7: ='Source Data'!$B$11 | J7: ='Source Data'!$B$12 | K7: ='Source Data'!$B$13 | L7: ='Source Data'!$B$14 | M7: ='Source Data'!$B$15 | N7: ='Source Data'!$B$16
A8: Course revenue | C8: ='Source Data'!$C$5 | D8: ='Source Data'!$C$6 | E8: ='Source Data'!$C$7 | F8: ='Source Data'!$C$8 | G8: ='Source Data'!$C$9 | H8: ='Source Data'!$C$10 | I8: ='Source Data'!$C$11 | J8: ='Source Data'!$C$12 | K8: ='Source Data'!$C$13 | L8: ='Source Data'!$C$14 | M8: ='Source Data'!$C$15 | N8: ='Source Data'!$C$16
A9: Hardware revenue | C9: ='Source Data'!$D$5 | D9: ='Source Data'!$D$6 | E9: ='Source Data'!$D$7 | F9: ='Source Data'!$D$8 | G9: ='Source Data'!$D$9 | H9: ='Source Data'!$D$10 | I9: ='Source Data'!$D$11 | J9: ='Source Data'!$D$12 | K9: ='Source Data'!$D$13 | L9: ='Source Data'!$D$14 | M9: ='Source Data'!$D$15 | N9: ='Source Data'!$D$16
A10: Total revenue | C10: =C8+C9 | D10: =D8+D9 | E10: =E8+E9 | F10: =F8+F9 | G10: =G8+G9 | H10: =H8+H9 | I10: =I8+I9 | J10: =J8+J9 | ... N10: =N8+N9
A11: Cost of Sales
A12: Course COGS | C12: ='Source Data'!$F$5 | D12: ='Source Data'!$F$6 | E12: ='Source Data'!$F$7 | F12: ='Source Data'!$F$8 | G12: ='Source Data'!$F$9 | H12: ='Source Data'!$F$10 | I12: ='Source Data'!$F$11 | J12: ='Source Data'!$F$12 | K12: ='Source Data'!$F$13 | L12: ='Source Data'!$F$14 | M12: ='Source Data'!$F$15 | N12: ='Source Data'!$F$16
A13: Hardware COGS | C13: ='Source Data'!$G$5 | D13: ='Source Data'!$G$6 | E13: ='Source Data'!$G$7 | F13: ='Source Data'!$G$8 | G13: ='Source Data'!$G$9 | H13: ='Source Data'!$G$10 | I13: ='Source Data'!$G$11 | J13: ='Source Data'!$G$12 | K13: ='Source Data'!$G$13 | L13: ='Source Data'!$G$14 | M13: ='Source Data'!$G$15 | N13: ='Source Data'!$G$16
A14: Logistics cost | C14: ='Source Data'!$H$5 | D14: ='Source Data'!$H$6 | E14: ='Source Data'!$H$7 | F14: ='Source Data'!$H$8 | G14: ='Source Data'!$H$9 | H14: ='Source Data'!$H$10 | I14: ='Source Data'!$H$11 | J14: ='Source Data'!$H$12 | K14: ='Source Data'!$H$13 | L14: ='Source Data'!$H$14 | M14: ='Source Data'!$H$15 | N14: ='Source Data'!$H$16
A15: Payment fee | C15: ='Source Data'!$I$5 | D15: ='Source Data'!$I$6 | E15: ='Source Data'!$I$7 | F15: ='Source Data'!$I$8 | G15: ='Source Data'!$I$9 | H15: ='Source Data'!$I$10 | I15: ='Source Data'!$I$11 | J15: ='Source Data'!$I$12 | K15: ='Source Data'!$I$13 | L15: ='Source Data'!$I$14 | M15: ='Source Data'!$I$15 | N15: ='Source Data'!$I$16
A16: Total COGS | C16: =SUM(C12:C15) | D16: =SUM(D12:D15) | E16: =SUM(E12:E15) | F16: =SUM(F12:F15) | G16: =SUM(G12:G15) | H16: =SUM(H12:H15) | I16: =SUM(I12:I15) | J16: =SUM(J12:J15) | ... N16: =SUM(N12:N15)
A17: Gross profit | C17: =C10-C16 | D17: =D10-D16 | E17: =E10-E16 | F17: =F10-F16 | G17: =G10-G16 | H17: =H10-H16 | I17: =I10-I16 | J17: =J10-J16 | ... N17: =N10-N16
A18: Gross margin % | C18: =IFERROR(C17/C10,0) | D18: =IFERROR(D17/D10,0) | E18: =IFERROR(E17/E10,0) | F18: =IFERROR(F17/F10,0) | G18: =IFERROR(G17/G10,0) | H18: =IFERROR(H17/H10,0) | I18: =IFERROR(I17/I10,0) | J18: =IFERROR(J17/J10,0) | ... N18: =IFERROR(N17/N10,0)
A20: Operating Expenses
A21: Team cost | C21: ='Source Data'!$L$5 | D21: ='Source Data'!$L$6 | E21: ='Source Data'!$L$7 | F21: ='Source Data'!$L$8 | G21: ='Source Data'!$L$9 | H21: ='Source Data'!$L$10 | I21: ='Source Data'!$L$11 | J21: ='Source Data'!$L$12 | K21: ='Source Data'!$L$13 | L21: ='Source Data'!$L$14 | M21: ='Source Data'!$L$15 | N21: ='Source Data'!$L$16
A22: Infra / tools | C22: ='Source Data'!$M$5 | D22: ='Source Data'!$M$6 | E22: ='Source Data'!$M$7 | F22: ='Source Data'!$M$8 | G22: ='Source Data'!$M$9 | H22: ='Source Data'!$M$10 | I22: ='Source Data'!$M$11 | J22: ='Source Data'!$M$12 | K22: ='Source Data'!$M$13 | L22: ='Source Data'!$M$14 | M22: ='Source Data'!$M$15 | N22: ='Source Data'!$M$16
A23: Marketing | C23: ='Source Data'!$N$5 | D23: ='Source Data'!$N$6 | E23: ='Source Data'!$N$7 | F23: ='Source Data'!$N$8 | G23: ='Source Data'!$N$9 | H23: ='Source Data'!$N$10 | I23: ='Source Data'!$N$11 | J23: ='Source Data'!$N$12 | K23: ='Source Data'!$N$13 | L23: ='Source Data'!$N$14 | M23: ='Source Data'!$N$15 | N23: ='Source Data'!$N$16
A24: Other opex | C24: ='Source Data'!$O$5 | D24: ='Source Data'!$O$6 | E24: ='Source Data'!$O$7 | F24: ='Source Data'!$O$8 | G24: ='Source Data'!$O$9 | H24: ='Source Data'!$O$10 | I24: ='Source Data'!$O$11 | J24: ='Source Data'!$O$12 | K24: ='Source Data'!$O$13 | L24: ='Source Data'!$O$14 | M24: ='Source Data'!$O$15 | N24: ='Source Data'!$O$16
A25: Total opex | C25: =SUM(C21:C24) | D25: =SUM(D21:D24) | E25: =SUM(E21:E24) | F25: =SUM(F21:F24) | G25: =SUM(G21:G24) | H25: =SUM(H21:H24) | I25: =SUM(I21:I24) | J25: =SUM(J21:J24) | ... N25: =SUM(N21:N24)
A26: EBITDA | C26: =C17-C25 | D26: =D17-D25 | E26: =E17-E25 | F26: =F17-F25 | G26: =G17-G25 | H26: =H17-H25 | I26: =I17-I25 | J26: =J17-J25 | ... N26: =N17-N25
A27: EBITDA margin % | C27: =IFERROR(C26/C10,0) | D27: =IFERROR(D26/D10,0) | E27: =IFERROR(E26/E10,0) | F27: =IFERROR(F26/F10,0) | G27: =IFERROR(G26/G10,0) | H27: =IFERROR(H26/H10,0) | I27: =IFERROR(I26/I10,0) | J27: =IFERROR(J26/J10,0) | ... N27: =IFERROR(N26/N10,0)
A29: Memo / Cash
A30: Cash injection (memo) | C30: ='Source Data'!$R$5 | D30: ='Source Data'!$R$6 | E30: ='Source Data'!$R$7 | F30: ='Source Data'!$R$8 | G30: ='Source Data'!$R$9 | H30: ='Source Data'!$R$10 | I30: ='Source Data'!$R$11 | J30: ='Source Data'!$R$12 | K30: ='Source Data'!$R$13 | L30: ='Source Data'!$R$14 | M30: ='Source Data'!$R$15 | N30: ='Source Data'!$R$16
A31: Ending cash (memo) | C31: ='Source Data'!$S$5 | D31: ='Source Data'!$S$6 | E31: ='Source Data'!$S$7 | F31: ='Source Data'!$S$8 | G31: ='Source Data'!$S$9 | H31: ='Source Data'!$S$10 | I31: ='Source Data'!$S$11 | J31: ='Source Data'!$S$12 | K31: ='Source Data'!$S$13 | L31: ='Source Data'!$S$14 | M31: ='Source Data'!$S$15 | N31: ='Source Data'!$S$16

Sheet Checks
A1: Checks
A3: Check | B3: Actual | C3: Expected | D3: Difference | E3: Tolerance | F3: Status | G3: Notes
A4: Revenue tie | B4: =SUM('Monthly P&L'!C10:N10) | C4: =SUM('Monthly P&L'!C8:N8)+SUM('Monthly P&L'!C9:N9) | D4: =B4-C4 | E4: 1 | F4: =IF(ABS(D4)<=E4,"OK","FAIL") | G4: Total revenue should equal course + hardware revenue.
A5: Gross profit tie | B5: =SUM('Monthly P&L'!C17:N17) | C5: =SUM('Monthly P&L'!C10:N10)-SUM('Monthly P&L'!C16:N16) | D5: =B5-C5 | E5: 1 | F5: =IF(ABS(D5)<=E5,"OK","FAIL") | G5: Gross profit should equal revenue minus COGS.
A6: EBITDA tie | B6: =SUM('Monthly P&L'!C26:N26) | C6: =SUM('Monthly P&L'!C17:N17)-SUM('Monthly P&L'!C25:N25) | D6: =B6-C6 | E6: 1 | F6: =IF(ABS(D6)<=E6,"OK","FAIL") | G6: EBITDA should equal gross profit minus opex.
A7: Closing cash tie | B7: ='Monthly P&L'!N31 | C7: ='Source Data'!S13 | D7: =B7-C7 | E7: 1 | F7: =IF(ABS(D7)<=E7,"OK","FAIL") | G7: Final cash should match the source plan.
A10: Model status | B10: =IF(COUNTIF(F4:F7,"FAIL")>0,"CHECK","OK")
